MANIFEST.in
README.rst
pstats2.py
setup.py
test_pstats2.py
pstats2.egg-info/PKG-INFO
pstats2.egg-info/SOURCES.txt
pstats2.egg-info/dependency_links.txt
pstats2.egg-info/requires.txt
pstats2.egg-info/top_level.txt