Metadata-Version: 1.1
Name: pstats2
Version: 0.1.0
Summary: pstats + modifications
Home-page: http://github.com/jstasiak/pstats2
Author: Jakub Stasiak
Author-email: jakub@stasiak.at
License: Apache License, Version 2.0
Download-URL: http://pypi.python.org/pypi/pstats2
Platform: any
